modelmetricsdk/__init__.py
modelmetricsdk/artifact_manager.py
modelmetricsdk/model_metrics_sdk.py
modelmetricsdk/sdk_exception.py
modelmetricsdk/singleton_manager.py
modelmetricsdk/storage_factory.py
modelmetricsdk/adapters/__init__.py
modelmetricsdk/adapters/base_adapter.py
modelmetricsdk/adapters/s3_adapter.py
modelmetricsdk/config/config.json
modelmetricsdk_subhash-0.3.dist-info/licenses/LICENSES.txt
modelmetricsdk_subhash-0.3.dist-info/METADATA
modelmetricsdk_subhash-0.3.dist-info/WHEEL
modelmetricsdk_subhash-0.3.dist-info/top_level.txt
modelmetricsdk_subhash-0.3.dist-info/RECORD
