Metadata-Version: 2.4
Name: modelmetricsdk_subhash
Version: 0.3
Summary: model store SDK for Training Host
Home-page: 
Author: O-RAN Software Community
Author-email: discuss@lists.o-ran-sc.org
License: Apache 2.0
License-File: LICENSES.txt
Requires-Dist: boto3
Requires-Dist: kubernetes
Requires-Dist: pyyaml
Dynamic: author
Dynamic: author-email
Dynamic: description
Dynamic: description-content-type
Dynamic: license
Dynamic: license-file
Dynamic: requires-dist
Dynamic: summary
